deepgrp/__init__.py
deepgrp/__main__.py
deepgrp/_mss/mss.c
deepgrp/_mss/mss.h
deepgrp/_mss/pymss.pyx
deepgrp/_scripts/__init__.py
deepgrp/_scripts/parse_rm.py
deepgrp/_scripts/preprocess_sequence.py
deepgrp/maxcalc.c
deepgrp/maxcalc.h
deepgrp/model.py
deepgrp/mss.pxd
deepgrp/mss.pyi
deepgrp/optimization.py
deepgrp/prediction.py
deepgrp/preprocessing.py
deepgrp/sequence.pyi
deepgrp/sequence.pyx
deepgrp/training.py
deepgrp/sequence.c
deepgrp/mss.cpython-38-x86_64-linux-gnu.so
deepgrp/sequence.cpython-38-x86_64-linux-gnu.so
deepgrp-0.2.3.dist-info/entry_points.txt
deepgrp-0.2.3.dist-info/LICENSE
deepgrp-0.2.3.dist-info/WHEEL
deepgrp-0.2.3.dist-info/METADATA
deepgrp-0.2.3.dist-info/RECORD
