Metadata-Version: 2.1
Name: deepgrp
Version: 0.2.3
Summary: DNA repeat annotations
Home-page: https://github.com/fhausmann/deepgrp
License: Apache-2.0
Author: Fabian Hausmann
Author-email: fabian.hausmann@zmnh.uni-hamburg.de
Requires-Python: >=3.6.1,<3.9.0
Classifier: License :: OSI Approved :: Apache Software License
Classifier: Programming Language :: Python :: 3
Classifier: Programming Language :: Python :: 3.7
Classifier: Programming Language :: Python :: 3.8
Requires-Dist: hyperopt (>=0.2.3,<0.3.0)
Requires-Dist: numpy (<1.20.0)
Requires-Dist: pandas (>=1.0.1,<2.0.0)
Requires-Dist: tensorflow (>=2.1.0,<2.6.0)
Requires-Dist: toml (>=0.10.0,<0.11.0)
Project-URL: Repository, https://github.com/fhausmann/deepgrp
